[
    { "album": "Sticky Notes", "release": "2020", "img": "sticky_notes.jpeg", "itunes": "https://music.apple.com/us/album/sticky-notes-ep/1498839504", "spotify": "https://open.spotify.com/album/0XiXB8pFuaVjmNKK5r7NLN?si=5m2uHdH9RPWJ5MjVYmnxPg", "tidal": "https://tidal.com/browse/album/131193845", "amazon": "https://www.amazon.com/Sticky-Notes-Mx-Swimms/dp/B084R9W8D1" },
    { "album": "Beats to Fall in Love to", "release": "2019", "img": "bfl_cover.jpeg", "itunes": "https://music.apple.com/us/album/beats-to-fall-in-love-to-single/1470272441", "spotify": "https://open.spotify.com/album/2OT31R1lJGM9J9Otr9Em8R?si=YmwYoN-ITLab1ZhX6_-hog", "tidal": "https://tidal.com/browse/album/112188398", "amazon": "https://www.amazon.com/gp/product/B07TJD3VG8/ref=dm_ws_sp_ps_dp" },
    { "album": "Stay True", "release": "2019", "img": "stay_true_cover.jpeg", "itunes": "https://music.apple.com/us/album/stay-true-single/1462187070", "spotify": "https://open.spotify.com/album/0f0sIN0K9Aye0WOHWDd7w6?si=dhVkSNPGT6matUaM3Vs5rg", "tidal": "https://tidal.com/browse/album/108639769", "amazon": "https://www.amazon.com/gp/product/B07RBBS6F8/ref=dm_ws_sp_ps_dp" },
    { "album": "Distractions", "release": "2019", "img": "distractions_cover.jpeg", "itunes": "https://music.apple.com/us/album/distractions-single/1451253915", "spotify": "https://open.spotify.com/album/4NnmPBYtAImFqIxU3usmVz?si=ziBAEyQCTyGkl3qTLCdv3w", "tidal": "https://tidal.com/browse/album/103262255", "amazon": "https://www.amazon.com/gp/product/B07N871Z7L/ref=dm_ws_sp_ps_dp" },
    { "album": "Together", "release": "2018", "img": "together_cover.jpeg", "itunes": "https://music.apple.com/us/album/together-feat-elocin-single/1449425041", "spotify": "https://open.spotify.com/album/7BGGl2sjQfGa7U3jHhYYra?si=APiJD8V4St2p6vj2OzSh5w", "tidal": "https://tidal.com/browse/album/102366596", "amazon": "https://www.amazon.com/Together-feat-Elocin-Mx-Swimms/dp/B07MGDVSG2/ref=sr_1_10?dchild=1&keywords=Mx.Swimms&qid=1605856862&s=dmusic&search-type=ss&sr=1-10" }
]
